ez_aio/__init__.py
ez_aio/aio.py
ez_aio-0.0.2.dist-info/METADATA
ez_aio-0.0.2.dist-info/WHEEL
ez_aio-0.0.2.dist-info/top_level.txt
ez_aio-0.0.2.dist-info/RECORD
