Metadata-Version: 2.1
Name: ez-aio
Version: 0.0.2
Summary: Easiest way to make tons of get/post requests with aiohttp.
Home-page: https://www.github.com/wangyi041228/ez_aio
Author: E
Author-email: 18771051812@qq.com
Requires-Dist: aiohttp
